{
  "manifest": {
    "title": "My dapp",
    "jsPath": "dist/main.js",
    "cssPath": "dapp-blog.css",
    "htmlPath": "dapp-blog.html"
  },
  "options": {
    "platform": "rchain",
    "readOnlyHost": "http://localhost",
    "readOnlyHostHttpPort": "40403",
    "validatorHost": "http://localhost",
    "validatorHostHttpPort": "40403",
    "validatorHostgrpcProposePort": "40402",
    "private_key": "",
    "registry_uri": "registry URI for the update of the dapp manifest (logged by rnode after push has been ran)",
    "unforgeable_name_id": "unforgeable name ID, blockchain address of the dapp manifest"
  }
}
